raises/__init__.py
raises-0.2.dist-info/WHEEL
raises-0.2.dist-info/METADATA
raises-0.2.dist-info/RECORD
